Workbook
Name Aporte: Ferramenta_Investimento!$D$21
Name Patrimonio: Ferramenta_Investimento!$D$24
Name qtd_anos: Ferramenta_Investimento!$D$22
Name Rendimento_Carteira: Ferramenta_Investimento!$D$17
Name Sugestão_Investimento: Ferramenta_Investimento!$D$18
Name taxa_mensal: Ferramenta_Investimento!$D$23
Name Taxas_Cenarios: Tabela_suporte!$B$24:$B$26
Name Tipo_investidor: Tabela_suporte!$A$24:$A$26

Sheet Ferramenta_Investimento
B15: CONFIGURAÇÕES
B16: Salário | D16: 8000 | F16: % de investimento
B17: Rendimento Carteira | D17: 0.01 | F17: 0.3
B18: Sugestão de Investimento | D18: =D16*$F$17 -> 2400
B20: INVESTIMENTO MENSAL
B21: Quanto investir por mês? | D21: 2400
A22: 2 | B22: Por quantos anos? | D22: 5
A23: 5 | B23: Taxa de rendimento mensal? | D23: 0.01078
A24: 10 | B24: Patrimônio acumulado? | D24: =FV(taxa_mensal,ROUND(qtd_anos*12,0),Aporte*-1) -> 200999.57
A25: 20 | B25: Dividendos Mensais? | D25: =Patrimonio*Rendimento_Carteira -> 2009.9957
A26: 30
B27: CENÁRIOS | D27: DIVIDENDO
A28: 2 | B28: Quanto em 2 Anos? | C28: =FV(Rendimento_Carteira,ROUND($A28*12,0),Aporte*-1) -> 64736.316 | D28: =C28*Rendimento_Carteira -> 647.36316
A29: 5 | B29: Quanto em 5 Anos? | C29: =FV(Rendimento_Carteira,ROUND($A29*12,0),Aporte*-1) -> 196007.21 | D29: =C29*Rendimento_Carteira -> 1960.0721
A30: 10 | B30: Quanto em 10 Anos? | C30: =FV(Rendimento_Carteira,ROUND($A30*12,0),Aporte*-1) -> 552092.85 | D30: =C30*Rendimento_Carteira -> 5520.9285
A31: 20 | B31: Quanto em 20 Anos? | C31: =FV(Rendimento_Carteira,ROUND($A31*12,0),Aporte*-1) -> 2374212.9 | D31: =C31*Rendimento_Carteira -> 23742.129
A32: 30 | B32: Quanto em 30 Anos? | C32: =FV(Rendimento_Carteira,ROUND($A32*12,0),Aporte*-1) -> 8387913.9 | D32: =C32*Rendimento_Carteira -> 83879.139
B51: Perfil de Investidor | C51: Moderado
B52: VALOR A SER INVESTIDO | C52: 500
B54: TIPO DE FII | C54: Percentual Sugerido | D54: Valores
B55: PAPEL | C55: =VLOOKUP($C$51&"-"&B55,Tabela_suporte!$A$4:$D$21,4,FALSE) -> 0.32 | D55: =C55*$C$52 -> 160
B56: TIJOLO | C56: =VLOOKUP($C$51&"-"&B56,Tabela_suporte!$A$4:$D$21,4,FALSE) -> 0.35 | D56: =C56*$C$52 -> 175
B57: HÍBRIDOS | C57: =VLOOKUP($C$51&"-"&B57,Tabela_suporte!$A$4:$D$21,4,FALSE) -> 0.08 | D57: =C57*$C$52 -> 40
B58: FOFs | C58: =VLOOKUP($C$51&"-"&B58,Tabela_suporte!$A$4:$D$21,4,FALSE) -> 0.05 | D58: =C58*$C$52 -> 25
B59: DESENVOLVIMENTO | C59: =VLOOKUP($C$51&"-"&B59,Tabela_suporte!$A$4:$D$21,4,FALSE) -> 0.1 | D59: =C59*$C$52 -> 50
B60: HOTELARIAS | C60: =VLOOKUP($C$51&"-"&B60,Tabela_suporte!$A$4:$D$21,4,FALSE) -> 0.1 | D60: =C60*$C$52 -> 50
B82: Perfil de Investidor | C82: Moderado
B83: VALOR A SER INVESTIDO - 30% DO SÁLARIO | C83: =D18 -> 2400
B85: TIPO DE FII | C85: Percentual Sugerido | D85: Valores
B86: PAPEL | C86: =VLOOKUP($C$82&"-"&B86,Tabela_suporte!$A$4:$D$21,4,FALSE) -> 0.32 | D86: =C86*$C$83 -> 768
B87: TIJOLO | C87: =VLOOKUP($C$82&"-"&B87,Tabela_suporte!$A$4:$D$21,4,FALSE) -> 0.35 | D87: =C87*$C$83 -> 840
B88: HÍBRIDOS | C88: =VLOOKUP($C$82&"-"&B88,Tabela_suporte!$A$4:$D$21,4,FALSE) -> 0.08 | D88: =C88*$C$83 -> 192
B89: FOFs | C89: =VLOOKUP($C$82&"-"&B89,Tabela_suporte!$A$4:$D$21,4,FALSE) -> 0.05 | D89: =C89*$C$83 -> 120
B90: DESENVOLVIMENTO | C90: =VLOOKUP($C$82&"-"&B90,Tabela_suporte!$A$4:$D$21,4,FALSE) -> 0.1 | D90: =C90*$C$83 -> 240
B91: HOTELARIAS | C91: =VLOOKUP($C$82&"-"&B91,Tabela_suporte!$A$4:$D$21,4,FALSE) -> 0.1 | D91: =C91*$C$83 -> 240
A102: , 5

Sheet Tabela_suporte
A3: CHAVE | B3: PERFIL | C3: TIPO DE FII | D3: %
A4: =B4&"-"&C4 -> Conservador-PAPEL | B4: Conservador | C4: PAPEL | D4: 0.3
A5: =B5&"-"&C5 -> Conservador-TIJOLO | B5: Conservador | C5: TIJOLO | D5: 0.5
A6: =B6&"-"&C6 -> Conservador-HÍBRIDOS | B6: Conservador | C6: HÍBRIDOS | D6: 0.1
A7: =B7&"-"&C7 -> Conservador-FOFs | B7: Conservador | C7: FOFs | D7: 0.1
A8: =B8&"-"&C8 -> Conservador-DESENVOLVIMENTO | B8: Conservador | C8: DESENVOLVIMENTO | D8: 0
A9: =B9&"-"&C9 -> Conservador-HOTELARIAS | B9: Conservador | C9: HOTELARIAS | D9: 0
A10: =B10&"-"&C10 -> Moderado-PAPEL | B10: Moderado | C10: PAPEL | D10: 0.32
A11: =B11&"-"&C11 -> Moderado-TIJOLO | B11: Moderado | C11: TIJOLO | D11: 0.35
A12: =B12&"-"&C12 -> Moderado-HÍBRIDOS | B12: Moderado | C12: HÍBRIDOS | D12: 0.08
A13: =B13&"-"&C13 -> Moderado-FOFs | B13: Moderado | C13: FOFs | D13: 0.05
A14: =B14&"-"&C14 -> Moderado-DESENVOLVIMENTO | B14: Moderado | C14: DESENVOLVIMENTO | D14: 0.1
A15: =B15&"-"&C15 -> Moderado-HOTELARIAS | B15: Moderado | C15: HOTELARIAS | D15: 0.1
... A21: =B21&"-"&C21 -> Agressivo-HOTELARIAS | B21: Agressivo | C21: HOTELARIAS | D21: 0.1
A24: Conservador | B24: 0.006
A25: Moderado | B25: 0.008
A26: Agressivo | B26: 0.01
B29: Período | C29: Aumento vs. período anterior
A30: 0
A31: =Ferramenta_Investimento!C28 -> 64736.316 | B31: =Ferramenta_Investimento!A28&" anos" -> 2 anos | C31: 0
A32: =Ferramenta_Investimento!C29 -> 196007.21 | B32: =Ferramenta_Investimento!A29&" anos" -> 5 anos | C32: =IFERROR((A32-A31)/A31,"") -> 2.0277782
A33: =Ferramenta_Investimento!C30 -> 552092.85 | B33: =Ferramenta_Investimento!A30&" anos" -> 10 anos | C33: =IFERROR((A33-A32)/A32,"") -> 1.8166967
A34: =Ferramenta_Investimento!C31 -> 2374212.9 | B34: =Ferramenta_Investimento!A31&" anos" -> 20 anos | C34: =IFERROR((A34-A33)/A33,"") -> 3.3003869
A35: =Ferramenta_Investimento!C32 -> 8387913.9 | B35: =Ferramenta_Investimento!A32&" anos" -> 30 anos | C35: =IFERROR((A35-A34)/A34,"") -> 2.5329241

Sheet Chart Data
A1: Anos | B1: Conservador (0,60% a.m.) | C1: Base (0,80% a.m.) | D1: Otimista (1,00% a.m.)
A2: 0 | B2: =FV(Tabela_suporte!$B$24,$A2*12,-Ferramenta_Investimento!$C$82,0,0) -> #VALUE! | C2: =FV(Tabela_suporte!$B$25,$A2*12,-Ferramenta_Investimento!$C$82,0,0) -> #VALUE! | D2: =FV(Tabela_suporte!$B$26,$A2*12,-Ferramenta_Investimento!$C$82,0,0) -> #VALUE!
A3: 1 | B3: =FV(Tabela_suporte!$B$24,$A3*12,-Ferramenta_Investimento!$C$82,0,0) -> #VALUE! | C3: =FV(Tabela_suporte!$B$25,$A3*12,-Ferramenta_Investimento!$C$82,0,0) -> #VALUE! | D3: =FV(Tabela_suporte!$B$26,$A3*12,-Ferramenta_Investimento!$C$82,0,0) -> #VALUE!
A4: 2 | B4: =FV(Tabela_suporte!$B$24,$A4*12,-Ferramenta_Investimento!$C$82,0,0) -> #VALUE! | C4: =FV(Tabela_suporte!$B$25,$A4*12,-Ferramenta_Investimento!$C$82,0,0) -> #VALUE! | D4: =FV(Tabela_suporte!$B$26,$A4*12,-Ferramenta_Investimento!$C$82,0,0) -> #VALUE!
A5: 3 | B5: =FV(Tabela_suporte!$B$24,$A5*12,-Ferramenta_Investimento!$C$82,0,0) -> #VALUE! | C5: =FV(Tabela_suporte!$B$25,$A5*12,-Ferramenta_Investimento!$C$82,0,0) -> #VALUE! | D5: =FV(Tabela_suporte!$B$26,$A5*12,-Ferramenta_Investimento!$C$82,0,0) -> #VALUE!
A6: 4 | B6: =FV(Tabela_suporte!$B$24,$A6*12,-Ferramenta_Investimento!$C$82,0,0) -> #VALUE! | C6: =FV(Tabela_suporte!$B$25,$A6*12,-Ferramenta_Investimento!$C$82,0,0) -> #VALUE! | D6: =FV(Tabela_suporte!$B$26,$A6*12,-Ferramenta_Investimento!$C$82,0,0) -> #VALUE!
A7: 5 | B7: =FV(Tabela_suporte!$B$24,$A7*12,-Ferramenta_Investimento!$C$82,0,0) -> #VALUE! | C7: =FV(Tabela_suporte!$B$25,$A7*12,-Ferramenta_Investimento!$C$82,0,0) -> #VALUE! | D7: =FV(Tabela_suporte!$B$26,$A7*12,-Ferramenta_Investimento!$C$82,0,0) -> #VALUE!
A8: 6 | B8: =FV(Tabela_suporte!$B$24,$A8*12,-Ferramenta_Investimento!$C$82,0,0) -> #VALUE! | C8: =FV(Tabela_suporte!$B$25,$A8*12,-Ferramenta_Investimento!$C$82,0,0) -> #VALUE! | D8: =FV(Tabela_suporte!$B$26,$A8*12,-Ferramenta_Investimento!$C$82,0,0) -> #VALUE!
A9: 7 | B9: =FV(Tabela_suporte!$B$24,$A9*12,-Ferramenta_Investimento!$C$82,0,0) -> #VALUE! | C9: =FV(Tabela_suporte!$B$25,$A9*12,-Ferramenta_Investimento!$C$82,0,0) -> #VALUE! | D9: =FV(Tabela_suporte!$B$26,$A9*12,-Ferramenta_Investimento!$C$82,0,0) -> #VALUE!
A10: 8 | B10: =FV(Tabela_suporte!$B$24,$A10*12,-Ferramenta_Investimento!$C$82,0,0) -> #VALUE! | C10: =FV(Tabela_suporte!$B$25,$A10*12,-Ferramenta_Investimento!$C$82,0,0) -> #VALUE! | D10: =FV(Tabela_suporte!$B$26,$A10*12,-Ferramenta_Investimento!$C$82,0,0) -> #VALUE!
A11: 9 | B11: =FV(Tabela_suporte!$B$24,$A11*12,-Ferramenta_Investimento!$C$82,0,0) -> #VALUE! | C11: =FV(Tabela_suporte!$B$25,$A11*12,-Ferramenta_Investimento!$C$82,0,0) -> #VALUE! | D11: =FV(Tabela_suporte!$B$26,$A11*12,-Ferramenta_Investimento!$C$82,0,0) -> #VALUE!
A12: 10 | B12: =FV(Tabela_suporte!$B$24,$A12*12,-Ferramenta_Investimento!$C$82,0,0) -> #VALUE! | C12: =FV(Tabela_suporte!$B$25,$A12*12,-Ferramenta_Investimento!$C$82,0,0) -> #VALUE! | D12: =FV(Tabela_suporte!$B$26,$A12*12,-Ferramenta_Investimento!$C$82,0,0) -> #VALUE!
A13: 11 | B13: =FV(Tabela_suporte!$B$24,$A13*12,-Ferramenta_Investimento!$C$82,0,0) -> #VALUE! | C13: =FV(Tabela_suporte!$B$25,$A13*12,-Ferramenta_Investimento!$C$82,0,0) -> #VALUE! | D13: =FV(Tabela_suporte!$B$26,$A13*12,-Ferramenta_Investimento!$C$82,0,0) -> #VALUE!
... A32: 30 | B32: =FV(Tabela_suporte!$B$24,$A32*12,-Ferramenta_Investimento!$C$82,0,0) -> #VALUE! | C32: =FV(Tabela_suporte!$B$25,$A32*12,-Ferramenta_Investimento!$C$82,0,0) -> #VALUE! | D32: =FV(Tabela_suporte!$B$26,$A32*12,-Ferramenta_Investimento!$C$82,0,0) -> #VALUE!
